xshelftransects/__init__.py
xshelftransects/geometry.py
xshelftransects/isobath.py
xshelftransects/sampling.py
xshelftransects/transects.py
xshelftransects-0.1.2.dist-info/METADATA
xshelftransects-0.1.2.dist-info/WHEEL
xshelftransects-0.1.2.dist-info/licenses/LICENSE
xshelftransects-0.1.2.dist-info/RECORD
