Metadata-Version: 2.4
Name: xshelftransects
Version: 0.1.2
Summary: 
License-File: LICENSE
Author: Anthony Meza
Author-email: 64243783+anthony-meza@users.noreply.github.com
Requires-Python: >=3.11
Classifier: Programming Language :: Python :: 3
Classifier: Programming Language :: Python :: 3.11
Classifier: Programming Language :: Python :: 3.12
Classifier: Programming Language :: Python :: 3.13
Classifier: Programming Language :: Python :: 3.14
Requires-Dist: cartopy
Requires-Dist: contourpy
Requires-Dist: intake (>=2.0.8,<3.0.0)
Requires-Dist: intake-esm (>=2025.12.12,<2026.0.0)
Requires-Dist: intake-geopandas[all] (>=0.4.0,<0.5.0)
Requires-Dist: intake-xarray[all] (>=2.0.0,<3.0.0)
Requires-Dist: netcdf4 (<1.7.3)
Requires-Dist: pyarrow (<=19.0.0)
Requires-Dist: pyproj (<3.7)
Requires-Dist: requests (>=2.32.5,<3.0.0)
Requires-Dist: scipy (<=1.16.0)
Requires-Dist: xarray[complete]
